{
    "1": {
        "id": 1,
        "type": 26,
        "name": "",
        "icon": "",
        "shop_prefab": "",
        "game_prefab": "",
        "sort": 1,
        "free": 1,
        "rarity": 1,
        "cover": 0,
        "skill_list": []
    },
    "101": {
        "id": 101,
        "type": 26,
        "name": "",
        "icon": "",
        "shop_prefab": "",
        "game_prefab": "",
        "sort": 1,
        "free": 0,
        "rarity": 1,
        "cover": 0,
        "skill_list": [
            1001,
            2001
        ]
    },
    "102": {
        "id": 102,
        "type": 26,
        "name": "",
        "icon": "",
        "shop_prefab": "",
        "game_prefab": "",
        "sort": 2,
        "free": 0,
        "rarity": 2,
        "cover": 0,
        "skill_list": [
            1002,
            2002
        ]
    },
    "103": {
        "id": 103,
        "type": 26,
        "name": "",
        "icon": "",
        "shop_prefab": "",
        "game_prefab": "",
        "sort": 3,
        "free": 0,
        "rarity": 3,
        "cover": 0,
        "skill_list": [
            1003,
            2003
        ]
    },
    "104": {
        "id": 104,
        "type": 26,
        "name": "",
        "icon": "",
        "shop_prefab": "",
        "game_prefab": "",
        "sort": 4,
        "free": 0,
        "rarity": 4,
        "cover": 0,
        "skill_list": [
            1004,
            2004
        ]
    },
    "105": {
        "id": 105,
        "type": 26,
        "name": "",
        "icon": "",
        "shop_prefab": "",
        "game_prefab": "",
        "sort": 5,
        "free": 0,
        "rarity": 1,
        "cover": 0,
        "skill_list": [
            1005,
            2005
        ]
    },
    "106": {
        "id": 106,
        "type": 26,
        "name": "",
        "icon": "",
        "shop_prefab": "",
        "game_prefab": "",
        "sort": 6,
        "free": 0,
        "rarity": 2,
        "cover": 0,
        "skill_list": [
            1006,
            2006
        ]
    },
    "107": {
        "id": 107,
        "type": 26,
        "name": "",
        "icon": "",
        "shop_prefab": "",
        "game_prefab": "",
        "sort": 7,
        "free": 0,
        "rarity": 3,
        "cover": 0,
        "skill_list": [
            1007,
            2007
        ]
    },
    "108": {
        "id": 108,
        "type": 26,
        "name": "",
        "icon": "",
        "shop_prefab": "",
        "game_prefab": "",
        "sort": 8,
        "free": 0,
        "rarity": 4,
        "cover": 0,
        "skill_list": [
            1008,
            2008
        ]
    },
    "109": {
        "id": 109,
        "type": 26,
        "name": "",
        "icon": "",
        "shop_prefab": "",
        "game_prefab": "",
        "sort": 9,
        "free": 0,
        "rarity": 4,
        "cover": 1,
        "skill_list": [
            1009,
            1010,
            1011,
            1012,
            2009,
            2010,
            2011,
            2012
        ]
    },
    "110": {
        "id": 110,
        "type": 26,
        "name": "",
        "icon": "",
        "shop_prefab": "",
        "game_prefab": "",
        "sort": 10,
        "free": 0,
        "rarity": 1,
        "cover": 0,
        "skill_list": [
            1013,
            2013
        ]
    },
    "111": {
        "id": 111,
        "type": 26,
        "name": "",
        "icon": "",
        "shop_prefab": "",
        "game_prefab": "",
        "sort": 11,
        "free": 0,
        "rarity": 2,
        "cover": 0,
        "skill_list": [
            1014,
            2014
        ]
    },
    "112": {
        "id": 112,
        "type": 26,
        "name": "",
        "icon": "",
        "shop_prefab": "",
        "game_prefab": "",
        "sort": 12,
        "free": 0,
        "rarity": 3,
        "cover": 0,
        "skill_list": [
            1015,
            2015
        ]
    },
    "113": {
        "id": 113,
        "type": 26,
        "name": "",
        "icon": "",
        "shop_prefab": "",
        "game_prefab": "",
        "sort": 13,
        "free": 0,
        "rarity": 4,
        "cover": 0,
        "skill_list": [
            1016,
            2016
        ]
    }
}